lamin_validator/__init__.py
lamin_validator/_anndata_validator.py
lamin_validator/_lookup.py
lamin_validator/_register.py
lamin_validator/_validate.py
lamin_validator/_validator.py
lamin_validator/datasets.py
lamin_validator-0.2.1.dist-info/LICENSE
lamin_validator-0.2.1.dist-info/WHEEL
lamin_validator-0.2.1.dist-info/METADATA
lamin_validator-0.2.1.dist-info/RECORD
