Metadata-Version: 2.1
Name: lamin_validator
Version: 0.2.1
Summary: Validators built on LaminDB.
Author-email: Lamin Labs <open-source@lamin.ai>
Requires-Dist: lamindb[aws,bionty,jupyter]
Requires-Dist: pre-commit ; extra == "dev"
Requires-Dist: nox ; extra == "dev"
Requires-Dist: pytest>=6.0 ; extra == "dev"
Requires-Dist: pytest-cov ; extra == "dev"
Requires-Dist: nbproject_test ; extra == "dev"
Project-URL: Home, https://github.com/laminlabs/lamin-validator
Provides-Extra: dev
